{
  "version": "7",
  "dialect": "postgresql",
  "entries": [
    {
      "idx": 0,
      "version": "7",
      "when": 1781142022357,
      "tag": "0000_brief_goblin_queen",
      "breakpoints": true
    },
    {
      "idx": 1,
      "version": "7",
      "when": 1783517820707,
      "tag": "0001_busy_jack_murdock",
      "breakpoints": true
    },
    {
      "idx": 2,
      "version": "7",
      "when": 1783744977825,
      "tag": "0002_outgoing_abomination",
      "breakpoints": true
    },
    {
      "idx": 3,
      "version": "7",
      "when": 1783746223238,
      "tag": "0003_tiny_morg",
      "breakpoints": true
    }
  ]
}
